gguf_node/__init__.py
gguf_node/__main__.py
gguf_node-0.2.8.dist-info/LICENSE
gguf_node-0.2.8.dist-info/WHEEL
gguf_node-0.2.8.dist-info/METADATA
gguf_node-0.2.8.dist-info/RECORD
