Metadata-Version: 2.1
Name: gguf-node
Version: 0.2.8
Summary: gguf node for comfyui
Author-email: calcuis <info@calcu.io>
Classifier: License :: OSI Approved :: MIT License
Requires-Dist: tqdm
Project-URL: Download, https://github.com/calcuis/gguf/releases
Project-URL: GitHub, https://github.com/calcuis/gguf
Project-URL: Homepage, https://gguf.org
Project-URL: Issues, https://github.com/calcuis/gguf/issues
Project-URL: reddit, https://www.reddit.com/r/gguf
